README.rst
setup.cfg
setup.py
evil/__init__.py
evil/maths.py
evil/set.py
evil.egg-info/PKG-INFO
evil.egg-info/SOURCES.txt
evil.egg-info/dependency_links.txt
evil.egg-info/top_level.txt