Metadata-Version: 1.1
Name: evil
Version: 0.5
Summary: Expression eviluator
Home-page: https://github.com/icio/evil
Author: Paul Scott
Author-email: paul@duedil.com
License: MIT
Download-URL: https://github.com/icio/evil/tarball/0.5
Keywords: expression,eval,evaluate,math,set,graph
Platform: UNKNOWN
